news_summarizer/__init__.py
news_summarizer/main.py
news_summarizer/prompts.py
news_summarizer-2025.12.21150146.dist-info/METADATA
news_summarizer-2025.12.21150146.dist-info/WHEEL
news_summarizer-2025.12.21150146.dist-info/top_level.txt
news_summarizer-2025.12.21150146.dist-info/RECORD
