Metadata-Version: 2.4
Name: news-summarizer
Version: 2025.12.21150146
Summary: A new package designed to facilitate the generation of structured summaries and insights from user-provided news headlines or short articles. It uses pattern matching to ensure responses are consisten
Author-email: news-summarizer <hi@eugene.plus>
License: MIT
Project-URL: Homepage, https://github.com/chigwell/news-summarizer
Requires-Python: >=3.9
Requires-Dist: langchain-llm7>=0.0.0
Requires-Dist: llmatch-messages>=0.0.0
Requires-Dist: langchain-core>=0.3.0
